{"nodes": [{"id": "d_temp_devorbit_gitnexus_gitnexus_src_core_ingestion_cobol_cobol_preprocessor_ts", "label": "cobol-preprocessor.ts", "file_type": "code", "source_file": "D:\\temp\\devorbit\\GitNexus\\gitnexus\\src\\core\\ingestion\\cobol\\cobol-preprocessor.ts", "source_location": "L1"}, {"id": "cobol_cobol_preprocessor_cobolregexresults", "label": "CobolRegexResults", "file_type": "code", "source_file": "D:\\temp\\devorbit\\GitNexus\\gitnexus\\src\\core\\ingestion\\cobol\\cobol-preprocessor.ts", "source_location": "L35"}, {"id": "cobol_cobol_preprocessor_preprocesscobolsource", "label": "preprocessCobolSource()", "file_type": "code", "source_file": "D:\\temp\\devorbit\\GitNexus\\gitnexus\\src\\core\\ingestion\\cobol\\cobol-preprocessor.ts", "source_location": "L205"}, {"id": "cobol_cobol_preprocessor_using_keywords", "label": "USING_KEYWORDS", "file_type": "code", "source_file": "D:\\temp\\devorbit\\GitNexus\\gitnexus\\src\\core\\ingestion\\cobol\\cobol-preprocessor.ts", "source_location": "L233"}, {"id": "cobol_cobol_preprocessor_call_using_filter", "label": "CALL_USING_FILTER", "file_type": "code", "source_file": "D:\\temp\\devorbit\\GitNexus\\gitnexus\\src\\core\\ingestion\\cobol\\cobol-preprocessor.ts", "source_location": "L244"}, {"id": "cobol_cobol_preprocessor_excluded_para_names", "label": "EXCLUDED_PARA_NAMES", "file_type": "code", "source_file": "D:\\temp\\devorbit\\GitNexus\\gitnexus\\src\\core\\ingestion\\cobol\\cobol-preprocessor.ts", "source_location": "L255"}, {"id": "cobol_cobol_preprocessor_division", "label": "Division", "file_type": "code", "source_file": "D:\\temp\\devorbit\\GitNexus\\gitnexus\\src\\core\\ingestion\\cobol\\cobol-preprocessor.ts", "source_location": "L294"}, {"id": "cobol_cobol_preprocessor_datasection", "label": "DataSection", "file_type": "code", "source_file": "D:\\temp\\devorbit\\GitNexus\\gitnexus\\src\\core\\ingestion\\cobol\\cobol-preprocessor.ts", "source_location": "L296"}, {"id": "cobol_cobol_preprocessor_environmentsection", "label": "EnvironmentSection", "file_type": "code", "source_file": "D:\\temp\\devorbit\\GitNexus\\gitnexus\\src\\core\\ingestion\\cobol\\cobol-preprocessor.ts", "source_location": "L298"}, {"id": "cobol_cobol_preprocessor_initialize_clause_keywords", "label": "INITIALIZE_CLAUSE_KEYWORDS", "file_type": "code", "source_file": "D:\\temp\\devorbit\\GitNexus\\gitnexus\\src\\core\\ingestion\\cobol\\cobol-preprocessor.ts", "source_location": "L389"}, {"id": "cobol_cobol_preprocessor_move_skip", "label": "MOVE_SKIP", "file_type": "code", "source_file": "D:\\temp\\devorbit\\GitNexus\\gitnexus\\src\\core\\ingestion\\cobol\\cobol-preprocessor.ts", "source_location": "L413"}, {"id": "cobol_cobol_preprocessor_extractmovetargets", "label": "extractMoveTargets()", "file_type": "code", "source_file": "D:\\temp\\devorbit\\GitNexus\\gitnexus\\src\\core\\ingestion\\cobol\\cobol-preprocessor.ts", "source_location": "L431"}, {"id": "cobol_cobol_preprocessor_perform_keyword_skip", "label": "PERFORM_KEYWORD_SKIP", "file_type": "code", "source_file": "D:\\temp\\devorbit\\GitNexus\\gitnexus\\src\\core\\ingestion\\cobol\\cobol-preprocessor.ts", "source_location": "L462"}, {"id": "cobol_cobol_preprocessor_sort_clause_noise", "label": "SORT_CLAUSE_NOISE", "file_type": "code", "source_file": "D:\\temp\\devorbit\\GitNexus\\gitnexus\\src\\core\\ingestion\\cobol\\cobol-preprocessor.ts", "source_location": "L465"}, {"id": "cobol_cobol_preprocessor_cobol_statement_verbs", "label": "COBOL_STATEMENT_VERBS", "file_type": "code", "source_file": "D:\\temp\\devorbit\\GitNexus\\gitnexus\\src\\core\\ingestion\\cobol\\cobol-preprocessor.ts", "source_location": "L491"}, {"id": "cobol_cobol_preprocessor_re_statement_verb_start", "label": "RE_STATEMENT_VERB_START", "file_type": "code", "source_file": "D:\\temp\\devorbit\\GitNexus\\gitnexus\\src\\core\\ingestion\\cobol\\cobol-preprocessor.ts", "source_location": "L527"}, {"id": "cobol_cobol_preprocessor_using_verb_lookahead", "label": "USING_VERB_LOOKAHEAD", "file_type": "code", "source_file": "D:\\temp\\devorbit\\GitNexus\\gitnexus\\src\\core\\ingestion\\cobol\\cobol-preprocessor.ts", "source_location": "L531"}, {"id": "cobol_cobol_preprocessor_re_using_params", "label": "RE_USING_PARAMS", "file_type": "code", "source_file": "D:\\temp\\devorbit\\GitNexus\\gitnexus\\src\\core\\ingestion\\cobol\\cobol-preprocessor.ts", "source_location": "L535"}, {"id": "cobol_cobol_preprocessor_stripinlinecomment", "label": "stripInlineComment()", "file_type": "code", "source_file": "D:\\temp\\devorbit\\GitNexus\\gitnexus\\src\\core\\ingestion\\cobol\\cobol-preprocessor.ts", "source_location": "L544"}, {"id": "cobol_cobol_preprocessor_parsedataitemclauses", "label": "parseDataItemClauses()", "file_type": "code", "source_file": "D:\\temp\\devorbit\\GitNexus\\gitnexus\\src\\core\\ingestion\\cobol\\cobol-preprocessor.ts", "source_location": "L563"}, {"id": "cobol_cobol_preprocessor_parseconditionvalues", "label": "parseConditionValues()", "file_type": "code", "source_file": "D:\\temp\\devorbit\\GitNexus\\gitnexus\\src\\core\\ingestion\\cobol\\cobol-preprocessor.ts", "source_location": "L671"}, {"id": "cobol_cobol_preprocessor_filedeclaration", "label": "FileDeclaration", "file_type": "code", "source_file": "D:\\temp\\devorbit\\GitNexus\\gitnexus\\src\\core\\ingestion\\cobol\\cobol-preprocessor.ts", "source_location": "L708"}, {"id": "cobol_cobol_preprocessor_parseselectstatement", "label": "parseSelectStatement()", "file_type": "code", "source_file": "D:\\temp\\devorbit\\GitNexus\\gitnexus\\src\\core\\ingestion\\cobol\\cobol-preprocessor.ts", "source_location": "L720"}, {"id": "cobol_cobol_preprocessor_sqloperation", "label": "SqlOperation", "file_type": "code", "source_file": "D:\\temp\\devorbit\\GitNexus\\gitnexus\\src\\core\\ingestion\\cobol\\cobol-preprocessor.ts", "source_location": "L777"}, {"id": "cobol_cobol_preprocessor_parseexecsqlblock", "label": "parseExecSqlBlock()", "file_type": "code", "source_file": "D:\\temp\\devorbit\\GitNexus\\gitnexus\\src\\core\\ingestion\\cobol\\cobol-preprocessor.ts", "source_location": "L788"}, {"id": "cobol_cobol_preprocessor_parseexeccicsblock", "label": "parseExecCicsBlock()", "file_type": "code", "source_file": "D:\\temp\\devorbit\\GitNexus\\gitnexus\\src\\core\\ingestion\\cobol\\cobol-preprocessor.ts", "source_location": "L868"}, {"id": "cobol_cobol_preprocessor_parseexecdliblock", "label": "parseExecDliBlock()", "file_type": "code", "source_file": "D:\\temp\\devorbit\\GitNexus\\gitnexus\\src\\core\\ingestion\\cobol\\cobol-preprocessor.ts", "source_location": "L960"}, {"id": "cobol_cobol_preprocessor_extractcobolsymbolswithregex", "label": "extractCobolSymbolsWithRegex()", "file_type": "code", "source_file": "D:\\temp\\devorbit\\GitNexus\\gitnexus\\src\\core\\ingestion\\cobol\\cobol-preprocessor.ts", "source_location": "L999"}], "edges": [{"source": "d_temp_devorbit_gitnexus_gitnexus_src_core_ingestion_cobol_cobol_preprocessor_ts", "target": "cobol_cobol_preprocessor_cobolregexresults", "relation": "contains", "confidence": "EXTRACTED", "source_file": "D:\\temp\\devorbit\\GitNexus\\gitnexus\\src\\core\\ingestion\\cobol\\cobol-preprocessor.ts", "source_location": "L35", "weight": 1.0}, {"source": "d_temp_devorbit_gitnexus_gitnexus_src_core_ingestion_cobol_cobol_preprocessor_ts", "target": "cobol_cobol_preprocessor_preprocesscobolsource", "relation": "contains", "confidence": "EXTRACTED", "source_file": "D:\\temp\\devorbit\\GitNexus\\gitnexus\\src\\core\\ingestion\\cobol\\cobol-preprocessor.ts", "source_location": "L205", "weight": 1.0}, {"source": "d_temp_devorbit_gitnexus_gitnexus_src_core_ingestion_cobol_cobol_preprocessor_ts", "target": "cobol_cobol_preprocessor_using_keywords", "relation": "contains", "confidence": "EXTRACTED", "source_file": "D:\\temp\\devorbit\\GitNexus\\gitnexus\\src\\core\\ingestion\\cobol\\cobol-preprocessor.ts", "source_location": "L233", "weight": 1.0}, {"source": "d_temp_devorbit_gitnexus_gitnexus_src_core_ingestion_cobol_cobol_preprocessor_ts", "target": "cobol_cobol_preprocessor_call_using_filter", "relation": "contains", "confidence": "EXTRACTED", "source_file": "D:\\temp\\devorbit\\GitNexus\\gitnexus\\src\\core\\ingestion\\cobol\\cobol-preprocessor.ts", "source_location": "L244", "weight": 1.0}, {"source": "d_temp_devorbit_gitnexus_gitnexus_src_core_ingestion_cobol_cobol_preprocessor_ts", "target": "cobol_cobol_preprocessor_excluded_para_names", "relation": "contains", "confidence": "EXTRACTED", "source_file": "D:\\temp\\devorbit\\GitNexus\\gitnexus\\src\\core\\ingestion\\cobol\\cobol-preprocessor.ts", "source_location": "L255", "weight": 1.0}, {"source": "d_temp_devorbit_gitnexus_gitnexus_src_core_ingestion_cobol_cobol_preprocessor_ts", "target": "cobol_cobol_preprocessor_division", "relation": "contains", "confidence": "EXTRACTED", "source_file": "D:\\temp\\devorbit\\GitNexus\\gitnexus\\src\\core\\ingestion\\cobol\\cobol-preprocessor.ts", "source_location": "L294", "weight": 1.0}, {"source": "d_temp_devorbit_gitnexus_gitnexus_src_core_ingestion_cobol_cobol_preprocessor_ts", "target": "cobol_cobol_preprocessor_datasection", "relation": "contains", "confidence": "EXTRACTED", "source_file": "D:\\temp\\devorbit\\GitNexus\\gitnexus\\src\\core\\ingestion\\cobol\\cobol-preprocessor.ts", "source_location": "L296", "weight": 1.0}, {"source": "d_temp_devorbit_gitnexus_gitnexus_src_core_ingestion_cobol_cobol_preprocessor_ts", "target": "cobol_cobol_preprocessor_environmentsection", "relation": "contains", "confidence": "EXTRACTED", "source_file": "D:\\temp\\devorbit\\GitNexus\\gitnexus\\src\\core\\ingestion\\cobol\\cobol-preprocessor.ts", "source_location": "L298", "weight": 1.0}, {"source": "d_temp_devorbit_gitnexus_gitnexus_src_core_ingestion_cobol_cobol_preprocessor_ts", "target": "cobol_cobol_preprocessor_initialize_clause_keywords", "relation": "contains", "confidence": "EXTRACTED", "source_file": "D:\\temp\\devorbit\\GitNexus\\gitnexus\\src\\core\\ingestion\\cobol\\cobol-preprocessor.ts", "source_location": "L389", "weight": 1.0}, {"source": "d_temp_devorbit_gitnexus_gitnexus_src_core_ingestion_cobol_cobol_preprocessor_ts", "target": "cobol_cobol_preprocessor_move_skip", "relation": "contains", "confidence": "EXTRACTED", "source_file": "D:\\temp\\devorbit\\GitNexus\\gitnexus\\src\\core\\ingestion\\cobol\\cobol-preprocessor.ts", "source_location": "L413", "weight": 1.0}, {"source": "d_temp_devorbit_gitnexus_gitnexus_src_core_ingestion_cobol_cobol_preprocessor_ts", "target": "cobol_cobol_preprocessor_extractmovetargets", "relation": "contains", "confidence": "EXTRACTED", "source_file": "D:\\temp\\devorbit\\GitNexus\\gitnexus\\src\\core\\ingestion\\cobol\\cobol-preprocessor.ts", "source_location": "L431", "weight": 1.0}, {"source": "d_temp_devorbit_gitnexus_gitnexus_src_core_ingestion_cobol_cobol_preprocessor_ts", "target": "cobol_cobol_preprocessor_perform_keyword_skip", "relation": "contains", "confidence": "EXTRACTED", "source_file": "D:\\temp\\devorbit\\GitNexus\\gitnexus\\src\\core\\ingestion\\cobol\\cobol-preprocessor.ts", "source_location": "L462", "weight": 1.0}, {"source": "d_temp_devorbit_gitnexus_gitnexus_src_core_ingestion_cobol_cobol_preprocessor_ts", "target": "cobol_cobol_preprocessor_sort_clause_noise", "relation": "contains", "confidence": "EXTRACTED", "source_file": "D:\\temp\\devorbit\\GitNexus\\gitnexus\\src\\core\\ingestion\\cobol\\cobol-preprocessor.ts", "source_location": "L465", "weight": 1.0}, {"source": "d_temp_devorbit_gitnexus_gitnexus_src_core_ingestion_cobol_cobol_preprocessor_ts", "target": "cobol_cobol_preprocessor_cobol_statement_verbs", "relation": "contains", "confidence": "EXTRACTED", "source_file": "D:\\temp\\devorbit\\GitNexus\\gitnexus\\src\\core\\ingestion\\cobol\\cobol-preprocessor.ts", "source_location": "L491", "weight": 1.0}, {"source": "d_temp_devorbit_gitnexus_gitnexus_src_core_ingestion_cobol_cobol_preprocessor_ts", "target": "cobol_cobol_preprocessor_re_statement_verb_start", "relation": "contains", "confidence": "EXTRACTED", "source_file": "D:\\temp\\devorbit\\GitNexus\\gitnexus\\src\\core\\ingestion\\cobol\\cobol-preprocessor.ts", "source_location": "L527", "weight": 1.0}, {"source": "d_temp_devorbit_gitnexus_gitnexus_src_core_ingestion_cobol_cobol_preprocessor_ts", "target": "cobol_cobol_preprocessor_using_verb_lookahead", "relation": "contains", "confidence": "EXTRACTED", "source_file": "D:\\temp\\devorbit\\GitNexus\\gitnexus\\src\\core\\ingestion\\cobol\\cobol-preprocessor.ts", "source_location": "L531", "weight": 1.0}, {"source": "d_temp_devorbit_gitnexus_gitnexus_src_core_ingestion_cobol_cobol_preprocessor_ts", "target": "cobol_cobol_preprocessor_re_using_params", "relation": "contains", "confidence": "EXTRACTED", "source_file": "D:\\temp\\devorbit\\GitNexus\\gitnexus\\src\\core\\ingestion\\cobol\\cobol-preprocessor.ts", "source_location": "L535", "weight": 1.0}, {"source": "d_temp_devorbit_gitnexus_gitnexus_src_core_ingestion_cobol_cobol_preprocessor_ts", "target": "cobol_cobol_preprocessor_stripinlinecomment", "relation": "contains", "confidence": "EXTRACTED", "source_file": "D:\\temp\\devorbit\\GitNexus\\gitnexus\\src\\core\\ingestion\\cobol\\cobol-preprocessor.ts", "source_location": "L544", "weight": 1.0}, {"source": "d_temp_devorbit_gitnexus_gitnexus_src_core_ingestion_cobol_cobol_preprocessor_ts", "target": "cobol_cobol_preprocessor_parsedataitemclauses", "relation": "contains", "confidence": "EXTRACTED", "source_file": "D:\\temp\\devorbit\\GitNexus\\gitnexus\\src\\core\\ingestion\\cobol\\cobol-preprocessor.ts", "source_location": "L563", "weight": 1.0}, {"source": "d_temp_devorbit_gitnexus_gitnexus_src_core_ingestion_cobol_cobol_preprocessor_ts", "target": "cobol_cobol_preprocessor_parseconditionvalues", "relation": "contains", "confidence": "EXTRACTED", "source_file": "D:\\temp\\devorbit\\GitNexus\\gitnexus\\src\\core\\ingestion\\cobol\\cobol-preprocessor.ts", "source_location": "L671", "weight": 1.0}, {"source": "d_temp_devorbit_gitnexus_gitnexus_src_core_ingestion_cobol_cobol_preprocessor_ts", "target": "cobol_cobol_preprocessor_filedeclaration", "relation": "contains", "confidence": "EXTRACTED", "source_file": "D:\\temp\\devorbit\\GitNexus\\gitnexus\\src\\core\\ingestion\\cobol\\cobol-preprocessor.ts", "source_location": "L708", "weight": 1.0}, {"source": "d_temp_devorbit_gitnexus_gitnexus_src_core_ingestion_cobol_cobol_preprocessor_ts", "target": "cobol_cobol_preprocessor_parseselectstatement", "relation": "contains", "confidence": "EXTRACTED", "source_file": "D:\\temp\\devorbit\\GitNexus\\gitnexus\\src\\core\\ingestion\\cobol\\cobol-preprocessor.ts", "source_location": "L720", "weight": 1.0}, {"source": "d_temp_devorbit_gitnexus_gitnexus_src_core_ingestion_cobol_cobol_preprocessor_ts", "target": "cobol_cobol_preprocessor_sqloperation", "relation": "contains", "confidence": "EXTRACTED", "source_file": "D:\\temp\\devorbit\\GitNexus\\gitnexus\\src\\core\\ingestion\\cobol\\cobol-preprocessor.ts", "source_location": "L777", "weight": 1.0}, {"source": "d_temp_devorbit_gitnexus_gitnexus_src_core_ingestion_cobol_cobol_preprocessor_ts", "target": "cobol_cobol_preprocessor_parseexecsqlblock", "relation": "contains", "confidence": "EXTRACTED", "source_file": "D:\\temp\\devorbit\\GitNexus\\gitnexus\\src\\core\\ingestion\\cobol\\cobol-preprocessor.ts", "source_location": "L788", "weight": 1.0}, {"source": "d_temp_devorbit_gitnexus_gitnexus_src_core_ingestion_cobol_cobol_preprocessor_ts", "target": "cobol_cobol_preprocessor_parseexeccicsblock", "relation": "contains", "confidence": "EXTRACTED", "source_file": "D:\\temp\\devorbit\\GitNexus\\gitnexus\\src\\core\\ingestion\\cobol\\cobol-preprocessor.ts", "source_location": "L868", "weight": 1.0}, {"source": "d_temp_devorbit_gitnexus_gitnexus_src_core_ingestion_cobol_cobol_preprocessor_ts", "target": "cobol_cobol_preprocessor_parseexecdliblock", "relation": "contains", "confidence": "EXTRACTED", "source_file": "D:\\temp\\devorbit\\GitNexus\\gitnexus\\src\\core\\ingestion\\cobol\\cobol-preprocessor.ts", "source_location": "L960", "weight": 1.0}, {"source": "d_temp_devorbit_gitnexus_gitnexus_src_core_ingestion_cobol_cobol_preprocessor_ts", "target": "cobol_cobol_preprocessor_extractcobolsymbolswithregex", "relation": "contains", "confidence": "EXTRACTED", "source_file": "D:\\temp\\devorbit\\GitNexus\\gitnexus\\src\\core\\ingestion\\cobol\\cobol-preprocessor.ts", "source_location": "L999", "weight": 1.0}, {"source": "cobol_cobol_preprocessor_extractcobolsymbolswithregex", "target": "cobol_cobol_preprocessor_stripinlinecomment", "relation": "calls", "context": "call", "confidence": "EXTRACTED", "source_file": "D:\\temp\\devorbit\\GitNexus\\gitnexus\\src\\core\\ingestion\\cobol\\cobol-preprocessor.ts", "source_location": "L1170", "weight": 1.0}, {"source": "cobol_cobol_preprocessor_extractcobolsymbolswithregex", "target": "cobol_cobol_preprocessor_parseexecsqlblock", "relation": "calls", "context": "call", "confidence": "EXTRACTED", "source_file": "D:\\temp\\devorbit\\GitNexus\\gitnexus\\src\\core\\ingestion\\cobol\\cobol-preprocessor.ts", "source_location": "L1197", "weight": 1.0}, {"source": "cobol_cobol_preprocessor_extractcobolsymbolswithregex", "target": "cobol_cobol_preprocessor_parseexeccicsblock", "relation": "calls", "context": "call", "confidence": "EXTRACTED", "source_file": "D:\\temp\\devorbit\\GitNexus\\gitnexus\\src\\core\\ingestion\\cobol\\cobol-preprocessor.ts", "source_location": "L1199", "weight": 1.0}, {"source": "cobol_cobol_preprocessor_extractcobolsymbolswithregex", "target": "cobol_cobol_preprocessor_parseexecdliblock", "relation": "calls", "context": "call", "confidence": "EXTRACTED", "source_file": "D:\\temp\\devorbit\\GitNexus\\gitnexus\\src\\core\\ingestion\\cobol\\cobol-preprocessor.ts", "source_location": "L1201", "weight": 1.0}], "raw_calls": [{"caller_nid": "cobol_cobol_preprocessor_preprocesscobolsource", "callee": "join", "is_member_call": true, "source_file": "D:\\temp\\devorbit\\GitNexus\\gitnexus\\src\\core\\ingestion\\cobol\\cobol-preprocessor.ts", "source_location": "L208"}, {"caller_nid": "cobol_cobol_preprocessor_preprocesscobolsource", "callee": "split", "is_member_call": true, "source_file": "D:\\temp\\devorbit\\GitNexus\\gitnexus\\src\\core\\ingestion\\cobol\\cobol-preprocessor.ts", "source_location": "L208"}, {"caller_nid": "cobol_cobol_preprocessor_preprocesscobolsource", "callee": "test", "is_member_call": true, "source_file": "D:\\temp\\devorbit\\GitNexus\\gitnexus\\src\\core\\ingestion\\cobol\\cobol-preprocessor.ts", "source_location": "L209"}, {"caller_nid": "cobol_cobol_preprocessor_preprocesscobolsource", "callee": "split", "is_member_call": true, "source_file": "D:\\temp\\devorbit\\GitNexus\\gitnexus\\src\\core\\ingestion\\cobol\\cobol-preprocessor.ts", "source_location": "L213"}, {"caller_nid": "cobol_cobol_preprocessor_preprocesscobolsource", "callee": "substring", "is_member_call": true, "source_file": "D:\\temp\\devorbit\\GitNexus\\gitnexus\\src\\core\\ingestion\\cobol\\cobol-preprocessor.ts", "source_location": "L217"}, {"caller_nid": "cobol_cobol_preprocessor_preprocesscobolsource", "callee": "test", "is_member_call": true, "source_file": "D:\\temp\\devorbit\\GitNexus\\gitnexus\\src\\core\\ingestion\\cobol\\cobol-preprocessor.ts", "source_location": "L221"}, {"caller_nid": "cobol_cobol_preprocessor_preprocesscobolsource", "callee": "substring", "is_member_call": true, "source_file": "D:\\temp\\devorbit\\GitNexus\\gitnexus\\src\\core\\ingestion\\cobol\\cobol-preprocessor.ts", "source_location": "L222"}, {"caller_nid": "cobol_cobol_preprocessor_preprocesscobolsource", "callee": "join", "is_member_call": true, "source_file": "D:\\temp\\devorbit\\GitNexus\\gitnexus\\src\\core\\ingestion\\cobol\\cobol-preprocessor.ts", "source_location": "L225"}, {"caller_nid": "cobol_cobol_preprocessor_extractmovetargets", "callee": "trim", "is_member_call": true, "source_file": "D:\\temp\\devorbit\\GitNexus\\gitnexus\\src\\core\\ingestion\\cobol\\cobol-preprocessor.ts", "source_location": "L433"}, {"caller_nid": "cobol_cobol_preprocessor_extractmovetargets", "callee": "replace", "is_member_call": true, "source_file": "D:\\temp\\devorbit\\GitNexus\\gitnexus\\src\\core\\ingestion\\cobol\\cobol-preprocessor.ts", "source_location": "L433"}, {"caller_nid": "cobol_cobol_preprocessor_extractmovetargets", "callee": "replace", "is_member_call": true, "source_file": "D:\\temp\\devorbit\\GitNexus\\gitnexus\\src\\core\\ingestion\\cobol\\cobol-preprocessor.ts", "source_location": "L437"}, {"caller_nid": "cobol_cobol_preprocessor_extractmovetargets", "callee": "filter", "is_member_call": true, "source_file": "D:\\temp\\devorbit\\GitNexus\\gitnexus\\src\\core\\ingestion\\cobol\\cobol-preprocessor.ts", "source_location": "L438"}, {"caller_nid": "cobol_cobol_preprocessor_extractmovetargets", "callee": "split", "is_member_call": true, "source_file": "D:\\temp\\devorbit\\GitNexus\\gitnexus\\src\\core\\ingestion\\cobol\\cobol-preprocessor.ts", "source_location": "L438"}, {"caller_nid": "cobol_cobol_preprocessor_extractmovetargets", "callee": "has", "is_member_call": true, "source_file": "D:\\temp\\devorbit\\GitNexus\\gitnexus\\src\\core\\ingestion\\cobol\\cobol-preprocessor.ts", "source_location": "L448"}, {"caller_nid": "cobol_cobol_preprocessor_extractmovetargets", "callee": "toUpperCase", "is_member_call": true, "source_file": "D:\\temp\\devorbit\\GitNexus\\gitnexus\\src\\core\\ingestion\\cobol\\cobol-preprocessor.ts", "source_location": "L448"}, {"caller_nid": "cobol_cobol_preprocessor_extractmovetargets", "callee": "test", "is_member_call": true, "source_file": "D:\\temp\\devorbit\\GitNexus\\gitnexus\\src\\core\\ingestion\\cobol\\cobol-preprocessor.ts", "source_location": "L452"}, {"caller_nid": "cobol_cobol_preprocessor_extractmovetargets", "callee": "has", "is_member_call": true, "source_file": "D:\\temp\\devorbit\\GitNexus\\gitnexus\\src\\core\\ingestion\\cobol\\cobol-preprocessor.ts", "source_location": "L452"}, {"caller_nid": "cobol_cobol_preprocessor_extractmovetargets", "callee": "toUpperCase", "is_member_call": true, "source_file": "D:\\temp\\devorbit\\GitNexus\\gitnexus\\src\\core\\ingestion\\cobol\\cobol-preprocessor.ts", "source_location": "L452"}, {"caller_nid": "cobol_cobol_preprocessor_extractmovetargets", "callee": "push", "is_member_call": true, "source_file": "D:\\temp\\devorbit\\GitNexus\\gitnexus\\src\\core\\ingestion\\cobol\\cobol-preprocessor.ts", "source_location": "L453"}, {"caller_nid": "cobol_cobol_preprocessor_stripinlinecomment", "callee": "substring", "is_member_call": true, "source_file": "D:\\temp\\devorbit\\GitNexus\\gitnexus\\src\\core\\ingestion\\cobol\\cobol-preprocessor.ts", "source_location": "L553"}, {"caller_nid": "cobol_cobol_preprocessor_parsedataitemclauses", "callee": "replace", "is_member_call": true, "source_file": "D:\\temp\\devorbit\\GitNexus\\gitnexus\\src\\core\\ingestion\\cobol\\cobol-preprocessor.ts", "source_location": "L585"}, {"caller_nid": "cobol_cobol_preprocessor_parsedataitemclauses", "callee": "match", "is_member_call": true, "source_file": "D:\\temp\\devorbit\\GitNexus\\gitnexus\\src\\core\\ingestion\\cobol\\cobol-preprocessor.ts", "source_location": "L588"}, {"caller_nid": "cobol_cobol_preprocessor_parsedataitemclauses", "callee": "match", "is_member_call": true, "source_file": "D:\\temp\\devorbit\\GitNexus\\gitnexus\\src\\core\\ingestion\\cobol\\cobol-preprocessor.ts", "source_location": "L594"}, {"caller_nid": "cobol_cobol_preprocessor_parsedataitemclauses", "callee": "toUpperCase", "is_member_call": true, "source_file": "D:\\temp\\devorbit\\GitNexus\\gitnexus\\src\\core\\ingestion\\cobol\\cobol-preprocessor.ts", "source_location": "L598"}, {"caller_nid": "cobol_cobol_preprocessor_parsedataitemclauses", "callee": "match", "is_member_call": true, "source_file": "D:\\temp\\devorbit\\GitNexus\\gitnexus\\src\\core\\ingestion\\cobol\\cobol-preprocessor.ts", "source_location": "L601"}, {"caller_nid": "cobol_cobol_preprocessor_parsedataitemclauses", "callee": "toUpperCase", "is_member_call": true, "source_file": "D:\\temp\\devorbit\\GitNexus\\gitnexus\\src\\core\\ingestion\\cobol\\cobol-preprocessor.ts", "source_location": "L603"}, {"caller_nid": "cobol_cobol_preprocessor_parsedataitemclauses", "callee": "match", "is_member_call": true, "source_file": "D:\\temp\\devorbit\\GitNexus\\gitnexus\\src\\core\\ingestion\\cobol\\cobol-preprocessor.ts", "source_location": "L608"}, {"caller_nid": "cobol_cobol_preprocessor_parsedataitemclauses", "callee": "match", "is_member_call": true, "source_file": "D:\\temp\\devorbit\\GitNexus\\gitnexus\\src\\core\\ingestion\\cobol\\cobol-preprocessor.ts", "source_location": "L614"}, {"caller_nid": "cobol_cobol_preprocessor_parsedataitemclauses", "callee": "parseInt", "is_member_call": false, "source_file": "D:\\temp\\devorbit\\GitNexus\\gitnexus\\src\\core\\ingestion\\cobol\\cobol-preprocessor.ts", "source_location": "L618"}, {"caller_nid": "cobol_cobol_preprocessor_parsedataitemclauses", "callee": "trim", "is_member_call": true, "source_file": "D:\\temp\\devorbit\\GitNexus\\gitnexus\\src\\core\\ingestion\\cobol\\cobol-preprocessor.ts", "source_location": "L621"}, {"caller_nid": "cobol_cobol_preprocessor_parsedataitemclauses", "callee": "replace", "is_member_call": true, "source_file": "D:\\temp\\devorbit\\GitNexus\\gitnexus\\src\\core\\ingestion\\cobol\\cobol-preprocessor.ts", "source_location": "L621"}, {"caller_nid": "cobol_cobol_preprocessor_parsedataitemclauses", "callee": "test", "is_member_call": true, "source_file": "D:\\temp\\devorbit\\GitNexus\\gitnexus\\src\\core\\ingestion\\cobol\\cobol-preprocessor.ts", "source_location": "L626"}, {"caller_nid": "cobol_cobol_preprocessor_parsedataitemclauses", "callee": "test", "is_member_call": true, "source_file": "D:\\temp\\devorbit\\GitNexus\\gitnexus\\src\\core\\ingestion\\cobol\\cobol-preprocessor.ts", "source_location": "L627"}, {"caller_nid": "cobol_cobol_preprocessor_parsedataitemclauses", "callee": "search", "is_member_call": true, "source_file": "D:\\temp\\devorbit\\GitNexus\\gitnexus\\src\\core\\ingestion\\cobol\\cobol-preprocessor.ts", "source_location": "L631"}, {"caller_nid": "cobol_cobol_preprocessor_parsedataitemclauses", "callee": "trimStart", "is_member_call": true, "source_file": "D:\\temp\\devorbit\\GitNexus\\gitnexus\\src\\core\\ingestion\\cobol\\cobol-preprocessor.ts", "source_location": "L633"}, {"caller_nid": "cobol_cobol_preprocessor_parsedataitemclauses", "callee": "replace", "is_member_call": true, "source_file": "D:\\temp\\devorbit\\GitNexus\\gitnexus\\src\\core\\ingestion\\cobol\\cobol-preprocessor.ts", "source_location": "L633"}, {"caller_nid": "cobol_cobol_preprocessor_parsedataitemclauses", "callee": "substring", "is_member_call": true, "source_file": "D:\\temp\\devorbit\\GitNexus\\gitnexus\\src\\core\\ingestion\\cobol\\cobol-preprocessor.ts", "source_location": "L633"}, {"caller_nid": "cobol_cobol_preprocessor_parsedataitemclauses", "callee": "match", "is_member_call": true, "source_file": "D:\\temp\\devorbit\\GitNexus\\gitnexus\\src\\core\\ingestion\\cobol\\cobol-preprocessor.ts", "source_location": "L638"}, {"caller_nid": "cobol_cobol_preprocessor_parsedataitemclauses", "callee": "toUpperCase", "is_member_call": true, "source_file": "D:\\temp\\devorbit\\GitNexus\\gitnexus\\src\\core\\ingestion\\cobol\\cobol-preprocessor.ts", "source_location": "L640"}, {"caller_nid": "cobol_cobol_preprocessor_parsedataitemclauses", "callee": "match", "is_member_call": true, "source_file": "D:\\temp\\devorbit\\GitNexus\\gitnexus\\src\\core\\ingestion\\cobol\\cobol-preprocessor.ts", "source_location": "L646"}, {"caller_nid": "cobol_cobol_preprocessor_parsedataitemclauses", "callee": "match", "is_member_call": true, "source_file": "D:\\temp\\devorbit\\GitNexus\\gitnexus\\src\\core\\ingestion\\cobol\\cobol-preprocessor.ts", "source_location": "L651"}, {"caller_nid": "cobol_cobol_preprocessor_parsedataitemclauses", "callee": "match", "is_member_call": true, "source_file": "D:\\temp\\devorbit\\GitNexus\\gitnexus\\src\\core\\ingestion\\cobol\\cobol-preprocessor.ts", "source_location": "L656"}, {"caller_nid": "cobol_cobol_preprocessor_parsedataitemclauses", "callee": "toUpperCase", "is_member_call": true, "source_file": "D:\\temp\\devorbit\\GitNexus\\gitnexus\\src\\core\\ingestion\\cobol\\cobol-preprocessor.ts", "source_location": "L657"}, {"caller_nid": "cobol_cobol_preprocessor_parseconditionvalues", "callee": "trim", "is_member_call": true, "source_file": "D:\\temp\\devorbit\\GitNexus\\gitnexus\\src\\core\\ingestion\\cobol\\cobol-preprocessor.ts", "source_location": "L673"}, {"caller_nid": "cobol_cobol_preprocessor_parseconditionvalues", "callee": "replace", "is_member_call": true, "source_file": "D:\\temp\\devorbit\\GitNexus\\gitnexus\\src\\core\\ingestion\\cobol\\cobol-preprocessor.ts", "source_location": "L673"}, {"caller_nid": "cobol_cobol_preprocessor_parseconditionvalues", "callee": "exec", "is_member_call": true, "source_file": "D:\\temp\\devorbit\\GitNexus\\gitnexus\\src\\core\\ingestion\\cobol\\cobol-preprocessor.ts", "source_location": "L680"}, {"caller_nid": "cobol_cobol_preprocessor_parseconditionvalues", "callee": "push", "is_member_call": true, "source_file": "D:\\temp\\devorbit\\GitNexus\\gitnexus\\src\\core\\ingestion\\cobol\\cobol-preprocessor.ts", "source_location": "L681"}, {"caller_nid": "cobol_cobol_preprocessor_parseconditionvalues", "callee": "split", "is_member_call": true, "source_file": "D:\\temp\\devorbit\\GitNexus\\gitnexus\\src\\core\\ingestion\\cobol\\cobol-preprocessor.ts", "source_location": "L688"}, {"caller_nid": "cobol_cobol_preprocessor_parseconditionvalues", "callee": "toUpperCase", "is_member_call": true, "source_file": "D:\\temp\\devorbit\\GitNexus\\gitnexus\\src\\core\\ingestion\\cobol\\cobol-preprocessor.ts", "source_location": "L690"}, {"caller_nid": "cobol_cobol_preprocessor_parseconditionvalues", "callee": "push", "is_member_call": true, "source_file": "D:\\temp\\devorbit\\GitNexus\\gitnexus\\src\\core\\ingestion\\cobol\\cobol-preprocessor.ts", "source_location": "L697"}, {"caller_nid": "cobol_cobol_preprocessor_parseselectstatement", "callee": "trim", "is_member_call": true, "source_file": "D:\\temp\\devorbit\\GitNexus\\gitnexus\\src\\core\\ingestion\\cobol\\cobol-preprocessor.ts", "source_location": "L722"}, {"caller_nid": "cobol_cobol_preprocessor_parseselectstatement", "callee": "replace", "is_member_call": true, "source_file": "D:\\temp\\devorbit\\GitNexus\\gitnexus\\src\\core\\ingestion\\cobol\\cobol-preprocessor.ts", "source_location": "L722"}, {"caller_nid": "cobol_cobol_preprocessor_parseselectstatement", "callee": "match", "is_member_call": true, "source_file": "D:\\temp\\devorbit\\GitNexus\\gitnexus\\src\\core\\ingestion\\cobol\\cobol-preprocessor.ts", "source_location": "L724"}, {"caller_nid": "cobol_cobol_preprocessor_parseselectstatement", "callee": "match", "is_member_call": true, "source_file": "D:\\temp\\devorbit\\GitNexus\\gitnexus\\src\\core\\ingestion\\cobol\\cobol-preprocessor.ts", "source_location": "L733"}, {"caller_nid": "cobol_cobol_preprocessor_parseselectstatement", "callee": "match", "is_member_call": true, "source_file": "D:\\temp\\devorbit\\GitNexus\\gitnexus\\src\\core\\ingestion\\cobol\\cobol-preprocessor.ts", "source_location": "L738"}, {"caller_nid": "cobol_cobol_preprocessor_parseselectstatement", "callee": "toUpperCase", "is_member_call": true, "source_file": "D:\\temp\\devorbit\\GitNexus\\gitnexus\\src\\core\\ingestion\\cobol\\cobol-preprocessor.ts", "source_location": "L742"}, {"caller_nid": "cobol_cobol_preprocessor_parseselectstatement", "callee": "match", "is_member_call": true, "source_file": "D:\\temp\\devorbit\\GitNexus\\gitnexus\\src\\core\\ingestion\\cobol\\cobol-preprocessor.ts", "source_location": "L745"}, {"caller_nid": "cobol_cobol_preprocessor_parseselectstatement", "callee": "toUpperCase", "is_member_call": true, "source_file": "D:\\temp\\devorbit\\GitNexus\\gitnexus\\src\\core\\ingestion\\cobol\\cobol-preprocessor.ts", "source_location": "L747"}, {"caller_nid": "cobol_cobol_preprocessor_parseselectstatement", "callee": "match", "is_member_call": true, "source_file": "D:\\temp\\devorbit\\GitNexus\\gitnexus\\src\\core\\ingestion\\cobol\\cobol-preprocessor.ts", "source_location": "L750"}, {"caller_nid": "cobol_cobol_preprocessor_parseselectstatement", "callee": "matchAll", "is_member_call": true, "source_file": "D:\\temp\\devorbit\\GitNexus\\gitnexus\\src\\core\\ingestion\\cobol\\cobol-preprocessor.ts", "source_location": "L756"}, {"caller_nid": "cobol_cobol_preprocessor_parseselectstatement", "callee": "push", "is_member_call": true, "source_file": "D:\\temp\\devorbit\\GitNexus\\gitnexus\\src\\core\\ingestion\\cobol\\cobol-preprocessor.ts", "source_location": "L758"}, {"caller_nid": "cobol_cobol_preprocessor_parseselectstatement", "callee": "match", "is_member_call": true, "source_file": "D:\\temp\\devorbit\\GitNexus\\gitnexus\\src\\core\\ingestion\\cobol\\cobol-preprocessor.ts", "source_location": "L762"}, {"caller_nid": "cobol_cobol_preprocessor_parseselectstatement", "callee": "test", "is_member_call": true, "source_file": "D:\\temp\\devorbit\\GitNexus\\gitnexus\\src\\core\\ingestion\\cobol\\cobol-preprocessor.ts", "source_location": "L768"}, {"caller_nid": "cobol_cobol_preprocessor_parseexecsqlblock", "callee": "trim", "is_member_call": true, "source_file": "D:\\temp\\devorbit\\GitNexus\\gitnexus\\src\\core\\ingestion\\cobol\\cobol-preprocessor.ts", "source_location": "L793"}, {"caller_nid": "cobol_cobol_preprocessor_parseexecsqlblock", "callee": "replace", "is_member_call": true, "source_file": "D:\\temp\\devorbit\\GitNexus\\gitnexus\\src\\core\\ingestion\\cobol\\cobol-preprocessor.ts", "source_location": "L793"}, {"caller_nid": "cobol_cobol_preprocessor_parseexecsqlblock", "callee": "replace", "is_member_call": true, "source_file": "D:\\temp\\devorbit\\GitNexus\\gitnexus\\src\\core\\ingestion\\cobol\\cobol-preprocessor.ts", "source_location": "L793"}, {"caller_nid": "cobol_cobol_preprocessor_parseexecsqlblock", "callee": "replace", "is_member_call": true, "source_file": "D:\\temp\\devorbit\\GitNexus\\gitnexus\\src\\core\\ingestion\\cobol\\cobol-preprocessor.ts", "source_location": "L793"}, {"caller_nid": "cobol_cobol_preprocessor_parseexecsqlblock", "callee": "toUpperCase", "is_member_call": true, "source_file": "D:\\temp\\devorbit\\GitNexus\\gitnexus\\src\\core\\ingestion\\cobol\\cobol-preprocessor.ts", "source_location": "L800"}, {"caller_nid": "cobol_cobol_preprocessor_parseexecsqlblock", "callee": "split", "is_member_call": true, "source_file": "D:\\temp\\devorbit\\GitNexus\\gitnexus\\src\\core\\ingestion\\cobol\\cobol-preprocessor.ts", "source_location": "L800"}, {"caller_nid": "cobol_cobol_preprocessor_parseexecsqlblock", "callee": "match", "is_member_call": true, "source_file": "D:\\temp\\devorbit\\GitNexus\\gitnexus\\src\\core\\ingestion\\cobol\\cobol-preprocessor.ts", "source_location": "L817"}, {"caller_nid": "cobol_cobol_preprocessor_parseexecsqlblock", "callee": "exec", "is_member_call": true, "source_file": "D:\\temp\\devorbit\\GitNexus\\gitnexus\\src\\core\\ingestion\\cobol\\cobol-preprocessor.ts", "source_location": "L833"}, {"caller_nid": "cobol_cobol_preprocessor_parseexecsqlblock", "callee": "toUpperCase", "is_member_call": true, "source_file": "D:\\temp\\devorbit\\GitNexus\\gitnexus\\src\\core\\ingestion\\cobol\\cobol-preprocessor.ts", "source_location": "L834"}, {"caller_nid": "cobol_cobol_preprocessor_parseexecsqlblock", "callee": "startsWith", "is_member_call": true, "source_file": "D:\\temp\\devorbit\\GitNexus\\gitnexus\\src\\core\\ingestion\\cobol\\cobol-preprocessor.ts", "source_location": "L836"}, {"caller_nid": "cobol_cobol_preprocessor_parseexecsqlblock", "callee": "includes", "is_member_call": true, "source_file": "D:\\temp\\devorbit\\GitNexus\\gitnexus\\src\\core\\ingestion\\cobol\\cobol-preprocessor.ts", "source_location": "L836"}, {"caller_nid": "cobol_cobol_preprocessor_parseexecsqlblock", "callee": "push", "is_member_call": true, "source_file": "D:\\temp\\devorbit\\GitNexus\\gitnexus\\src\\core\\ingestion\\cobol\\cobol-preprocessor.ts", "source_location": "L837"}, {"caller_nid": "cobol_cobol_preprocessor_parseexecsqlblock", "callee": "exec", "is_member_call": true, "source_file": "D:\\temp\\devorbit\\GitNexus\\gitnexus\\src\\core\\ingestion\\cobol\\cobol-preprocessor.ts", "source_location": "L846"}, {"caller_nid": "cobol_cobol_preprocessor_parseexecsqlblock", "callee": "push", "is_member_call": true, "source_file": "D:\\temp\\devorbit\\GitNexus\\gitnexus\\src\\core\\ingestion\\cobol\\cobol-preprocessor.ts", "source_location": "L847"}, {"caller_nid": "cobol_cobol_preprocessor_parseexecsqlblock", "callee": "exec", "is_member_call": true, "source_file": "D:\\temp\\devorbit\\GitNexus\\gitnexus\\src\\core\\ingestion\\cobol\\cobol-preprocessor.ts", "source_location": "L854"}, {"caller_nid": "cobol_cobol_preprocessor_parseexecsqlblock", "callee": "includes", "is_member_call": true, "source_file": "D:\\temp\\devorbit\\GitNexus\\gitnexus\\src\\core\\ingestion\\cobol\\cobol-preprocessor.ts", "source_location": "L856"}, {"caller_nid": "cobol_cobol_preprocessor_parseexecsqlblock", "callee": "push", "is_member_call": true, "source_file": "D:\\temp\\devorbit\\GitNexus\\gitnexus\\src\\core\\ingestion\\cobol\\cobol-preprocessor.ts", "source_location": "L857"}, {"caller_nid": "cobol_cobol_preprocessor_parseexeccicsblock", "callee": "trim", "is_member_call": true, "source_file": "D:\\temp\\devorbit\\GitNexus\\gitnexus\\src\\core\\ingestion\\cobol\\cobol-preprocessor.ts", "source_location": "L873"}, {"caller_nid": "cobol_cobol_preprocessor_parseexeccicsblock", "callee": "replace", "is_member_call": true, "source_file": "D:\\temp\\devorbit\\GitNexus\\gitnexus\\src\\core\\ingestion\\cobol\\cobol-preprocessor.ts", "source_location": "L873"}, {"caller_nid": "cobol_cobol_preprocessor_parseexeccicsblock", "callee": "replace", "is_member_call": true, "source_file": "D:\\temp\\devorbit\\GitNexus\\gitnexus\\src\\core\\ingestion\\cobol\\cobol-preprocessor.ts", "source_location": "L873"}, {"caller_nid": "cobol_cobol_preprocessor_parseexeccicsblock", "callee": "replace", "is_member_call": true, "source_file": "D:\\temp\\devorbit\\GitNexus\\gitnexus\\src\\core\\ingestion\\cobol\\cobol-preprocessor.ts", "source_location": "L873"}, {"caller_nid": "cobol_cobol_preprocessor_parseexeccicsblock", "callee": "toUpperCase", "is_member_call": true, "source_file": "D:\\temp\\devorbit\\GitNexus\\gitnexus\\src\\core\\ingestion\\cobol\\cobol-preprocessor.ts", "source_location": "L899"}, {"caller_nid": "cobol_cobol_preprocessor_parseexeccicsblock", "callee": "startsWith", "is_member_call": true, "source_file": "D:\\temp\\devorbit\\GitNexus\\gitnexus\\src\\core\\ingestion\\cobol\\cobol-preprocessor.ts", "source_location": "L901"}, {"caller_nid": "cobol_cobol_preprocessor_parseexeccicsblock", "callee": "toUpperCase", "is_member_call": true, "source_file": "D:\\temp\\devorbit\\GitNexus\\gitnexus\\src\\core\\ingestion\\cobol\\cobol-preprocessor.ts", "source_location": "L907"}, {"caller_nid": "cobol_cobol_preprocessor_parseexeccicsblock", "callee": "split", "is_member_call": true, "source_file": "D:\\temp\\devorbit\\GitNexus\\gitnexus\\src\\core\\ingestion\\cobol\\cobol-preprocessor.ts", "source_location": "L907"}, {"caller_nid": "cobol_cobol_preprocessor_parseexeccicsblock", "callee": "match", "is_member_call": true, "source_file": "D:\\temp\\devorbit\\GitNexus\\gitnexus\\src\\core\\ingestion\\cobol\\cobol-preprocessor.ts", "source_location": "L913"}, {"caller_nid": "cobol_cobol_preprocessor_parseexeccicsblock", "callee": "match", "is_member_call": true, "source_file": "D:\\temp\\devorbit\\GitNexus\\gitnexus\\src\\core\\ingestion\\cobol\\cobol-preprocessor.ts", "source_location": "L917"}, {"caller_nid": "cobol_cobol_preprocessor_parseexeccicsblock", "callee": "match", "is_member_call": true, "source_file": "D:\\temp\\devorbit\\GitNexus\\gitnexus\\src\\core\\ingestion\\cobol\\cobol-preprocessor.ts", "source_location": "L924"}, {"caller_nid": "cobol_cobol_preprocessor_parseexeccicsblock", "callee": "match", "is_member_call": true, "source_file": "D:\\temp\\devorbit\\GitNexus\\gitnexus\\src\\core\\ingestion\\cobol\\cobol-preprocessor.ts", "source_location": "L929"}, {"caller_nid": "cobol_cobol_preprocessor_parseexeccicsblock", "callee": "match", "is_member_call": true, "source_file": "D:\\temp\\devorbit\\GitNexus\\gitnexus\\src\\core\\ingestion\\cobol\\cobol-preprocessor.ts", "source_location": "L938"}, {"caller_nid": "cobol_cobol_preprocessor_parseexeccicsblock", "callee": "match", "is_member_call": true, "source_file": "D:\\temp\\devorbit\\GitNexus\\gitnexus\\src\\core\\ingestion\\cobol\\cobol-preprocessor.ts", "source_location": "L942"}, {"caller_nid": "cobol_cobol_preprocessor_parseexeccicsblock", "callee": "match", "is_member_call": true, "source_file": "D:\\temp\\devorbit\\GitNexus\\gitnexus\\src\\core\\ingestion\\cobol\\cobol-preprocessor.ts", "source_location": "L946"}, {"caller_nid": "cobol_cobol_preprocessor_parseexeccicsblock", "callee": "match", "is_member_call": true, "source_file": "D:\\temp\\devorbit\\GitNexus\\gitnexus\\src\\core\\ingestion\\cobol\\cobol-preprocessor.ts", "source_location": "L950"}, {"caller_nid": "cobol_cobol_preprocessor_parseexecdliblock", "callee": "trim", "is_member_call": true, "source_file": "D:\\temp\\devorbit\\GitNexus\\gitnexus\\src\\core\\ingestion\\cobol\\cobol-preprocessor.ts", "source_location": "L964"}, {"caller_nid": "cobol_cobol_preprocessor_parseexecdliblock", "callee": "replace", "is_member_call": true, "source_file": "D:\\temp\\devorbit\\GitNexus\\gitnexus\\src\\core\\ingestion\\cobol\\cobol-preprocessor.ts", "source_location": "L964"}, {"caller_nid": "cobol_cobol_preprocessor_parseexecdliblock", "callee": "replace", "is_member_call": true, "source_file": "D:\\temp\\devorbit\\GitNexus\\gitnexus\\src\\core\\ingestion\\cobol\\cobol-preprocessor.ts", "source_location": "L964"}, {"caller_nid": "cobol_cobol_preprocessor_parseexecdliblock", "callee": "replace", "is_member_call": true, "source_file": "D:\\temp\\devorbit\\GitNexus\\gitnexus\\src\\core\\ingestion\\cobol\\cobol-preprocessor.ts", "source_location": "L964"}, {"caller_nid": "cobol_cobol_preprocessor_parseexecdliblock", "callee": "toUpperCase", "is_member_call": true, "source_file": "D:\\temp\\devorbit\\GitNexus\\gitnexus\\src\\core\\ingestion\\cobol\\cobol-preprocessor.ts", "source_location": "L969"}, {"caller_nid": "cobol_cobol_preprocessor_parseexecdliblock", "callee": "split", "is_member_call": true, "source_file": "D:\\temp\\devorbit\\GitNexus\\gitnexus\\src\\core\\ingestion\\cobol\\cobol-preprocessor.ts", "source_location": "L969"}, {"caller_nid": "cobol_cobol_preprocessor_parseexecdliblock", "callee": "match", "is_member_call": true, "source_file": "D:\\temp\\devorbit\\GitNexus\\gitnexus\\src\\core\\ingestion\\cobol\\cobol-preprocessor.ts", "source_location": "L972"}, {"caller_nid": "cobol_cobol_preprocessor_parseexecdliblock", "callee": "parseInt", "is_member_call": false, "source_file": "D:\\temp\\devorbit\\GitNexus\\gitnexus\\src\\core\\ingestion\\cobol\\cobol-preprocessor.ts", "source_location": "L973"}, {"caller_nid": "cobol_cobol_preprocessor_parseexecdliblock", "callee": "match", "is_member_call": true, "source_file": "D:\\temp\\devorbit\\GitNexus\\gitnexus\\src\\core\\ingestion\\cobol\\cobol-preprocessor.ts", "source_location": "L975"}, {"caller_nid": "cobol_cobol_preprocessor_parseexecdliblock", "callee": "match", "is_member_call": true, "source_file": "D:\\temp\\devorbit\\GitNexus\\gitnexus\\src\\core\\ingestion\\cobol\\cobol-preprocessor.ts", "source_location": "L978"}, {"caller_nid": "cobol_cobol_preprocessor_parseexecdliblock", "callee": "match", "is_member_call": true, "source_file": "D:\\temp\\devorbit\\GitNexus\\gitnexus\\src\\core\\ingestion\\cobol\\cobol-preprocessor.ts", "source_location": "L981"}, {"caller_nid": "cobol_cobol_preprocessor_parseexecdliblock", "callee": "match", "is_member_call": true, "source_file": "D:\\temp\\devorbit\\GitNexus\\gitnexus\\src\\core\\ingestion\\cobol\\cobol-preprocessor.ts", "source_location": "L984"}, {"caller_nid": "cobol_cobol_preprocessor_extractcobolsymbolswithregex", "callee": "split", "is_member_call": true, "source_file": "D:\\temp\\devorbit\\GitNexus\\gitnexus\\src\\core\\ingestion\\cobol\\cobol-preprocessor.ts", "source_location": "L1003"}, {"caller_nid": "cobol_cobol_preprocessor_extractcobolsymbolswithregex", "callee": "min", "is_member_call": true, "source_file": "D:\\temp\\devorbit\\GitNexus\\gitnexus\\src\\core\\ingestion\\cobol\\cobol-preprocessor.ts", "source_location": "L1083"}, {"caller_nid": "cobol_cobol_preprocessor_extractcobolsymbolswithregex", "callee": "test", "is_member_call": true, "source_file": "D:\\temp\\devorbit\\GitNexus\\gitnexus\\src\\core\\ingestion\\cobol\\cobol-preprocessor.ts", "source_location": "L1084"}, {"caller_nid": "cobol_cobol_preprocessor_extractcobolsymbolswithregex", "callee": "test", "is_member_call": true, "source_file": "D:\\temp\\devorbit\\GitNexus\\gitnexus\\src\\core\\ingestion\\cobol\\cobol-preprocessor.ts", "source_location": "L1097"}, {"caller_nid": "cobol_cobol_preprocessor_extractcobolsymbolswithregex", "callee": "trimStart", "is_member_call": true, "source_file": "D:\\temp\\devorbit\\GitNexus\\gitnexus\\src\\core\\ingestion\\cobol\\cobol-preprocessor.ts", "source_location": "L1099"}, {"caller_nid": "cobol_cobol_preprocessor_extractcobolsymbolswithregex", "callee": "startsWith", "is_member_call": true, "source_file": "D:\\temp\\devorbit\\GitNexus\\gitnexus\\src\\core\\ingestion\\cobol\\cobol-preprocessor.ts", "source_location": "L1100"}, {"caller_nid": "cobol_cobol_preprocessor_extractcobolsymbolswithregex", "callee": "substring", "is_member_call": true, "source_file": "D:\\temp\\devorbit\\GitNexus\\gitnexus\\src\\core\\ingestion\\cobol\\cobol-preprocessor.ts", "source_location": "L1115"}, {"caller_nid": "cobol_cobol_preprocessor_extractcobolsymbolswithregex", "callee": "processLogicalLine", "is_member_call": false, "source_file": "D:\\temp\\devorbit\\GitNexus\\gitnexus\\src\\core\\ingestion\\cobol\\cobol-preprocessor.ts", "source_location": "L1118"}, {"caller_nid": "cobol_cobol_preprocessor_extractcobolsymbolswithregex", "callee": "trim", "is_member_call": true, "source_file": "D:\\temp\\devorbit\\GitNexus\\gitnexus\\src\\core\\ingestion\\cobol\\cobol-preprocessor.ts", "source_location": "L1118"}, {"caller_nid": "cobol_cobol_preprocessor_extractcobolsymbolswithregex", "callee": "processLogicalLine", "is_member_call": false, "source_file": "D:\\temp\\devorbit\\GitNexus\\gitnexus\\src\\core\\ingestion\\cobol\\cobol-preprocessor.ts", "source_location": "L1128"}, {"caller_nid": "cobol_cobol_preprocessor_extractcobolsymbolswithregex", "callee": "trimStart", "is_member_call": true, "source_file": "D:\\temp\\devorbit\\GitNexus\\gitnexus\\src\\core\\ingestion\\cobol\\cobol-preprocessor.ts", "source_location": "L1144"}, {"caller_nid": "cobol_cobol_preprocessor_extractcobolsymbolswithregex", "callee": "substring", "is_member_call": true, "source_file": "D:\\temp\\devorbit\\GitNexus\\gitnexus\\src\\core\\ingestion\\cobol\\cobol-preprocessor.ts", "source_location": "L1144"}, {"caller_nid": "cobol_cobol_preprocessor_extractcobolsymbolswithregex", "callee": "lastIndexOf", "is_member_call": true, "source_file": "D:\\temp\\devorbit\\GitNexus\\gitnexus\\src\\core\\ingestion\\cobol\\cobol-preprocessor.ts", "source_location": "L1149"}, {"caller_nid": "cobol_cobol_preprocessor_extractcobolsymbolswithregex", "callee": "substring", "is_member_call": true, "source_file": "D:\\temp\\devorbit\\GitNexus\\gitnexus\\src\\core\\ingestion\\cobol\\cobol-preprocessor.ts", "source_location": "L1151"}, {"caller_nid": "cobol_cobol_preprocessor_extractcobolsymbolswithregex", "callee": "substring", "is_member_call": true, "source_file": "D:\\temp\\devorbit\\GitNexus\\gitnexus\\src\\core\\ingestion\\cobol\\cobol-preprocessor.ts", "source_location": "L1151"}, {"caller_nid": "cobol_cobol_preprocessor_extractcobolsymbolswithregex", "callee": "processLogicalLine", "is_member_call": false, "source_file": "D:\\temp\\devorbit\\GitNexus\\gitnexus\\src\\core\\ingestion\\cobol\\cobol-preprocessor.ts", "source_location": "L1164"}, {"caller_nid": "cobol_cobol_preprocessor_extractcobolsymbolswithregex", "callee": "processLogicalLine", "is_member_call": false, "source_file": "D:\\temp\\devorbit\\GitNexus\\gitnexus\\src\\core\\ingestion\\cobol\\cobol-preprocessor.ts", "source_location": "L1179"}, {"caller_nid": "cobol_cobol_preprocessor_extractcobolsymbolswithregex", "callee": "flushSelect", "is_member_call": false, "source_file": "D:\\temp\\devorbit\\GitNexus\\gitnexus\\src\\core\\ingestion\\cobol\\cobol-preprocessor.ts", "source_location": "L1183"}, {"caller_nid": "cobol_cobol_preprocessor_extractcobolsymbolswithregex", "callee": "flushSort", "is_member_call": false, "source_file": "D:\\temp\\devorbit\\GitNexus\\gitnexus\\src\\core\\ingestion\\cobol\\cobol-preprocessor.ts", "source_location": "L1186"}, {"caller_nid": "cobol_cobol_preprocessor_extractcobolsymbolswithregex", "callee": "flushInspect", "is_member_call": false, "source_file": "D:\\temp\\devorbit\\GitNexus\\gitnexus\\src\\core\\ingestion\\cobol\\cobol-preprocessor.ts", "source_location": "L1189"}, {"caller_nid": "cobol_cobol_preprocessor_extractcobolsymbolswithregex", "callee": "flushCallAccum", "is_member_call": false, "source_file": "D:\\temp\\devorbit\\GitNexus\\gitnexus\\src\\core\\ingestion\\cobol\\cobol-preprocessor.ts", "source_location": "L1192"}, {"caller_nid": "cobol_cobol_preprocessor_extractcobolsymbolswithregex", "callee": "push", "is_member_call": true, "source_file": "D:\\temp\\devorbit\\GitNexus\\gitnexus\\src\\core\\ingestion\\cobol\\cobol-preprocessor.ts", "source_location": "L1197"}, {"caller_nid": "cobol_cobol_preprocessor_extractcobolsymbolswithregex", "callee": "push", "is_member_call": true, "source_file": "D:\\temp\\devorbit\\GitNexus\\gitnexus\\src\\core\\ingestion\\cobol\\cobol-preprocessor.ts", "source_location": "L1199"}, {"caller_nid": "cobol_cobol_preprocessor_extractcobolsymbolswithregex", "callee": "push", "is_member_call": true, "source_file": "D:\\temp\\devorbit\\GitNexus\\gitnexus\\src\\core\\ingestion\\cobol\\cobol-preprocessor.ts", "source_location": "L1201"}, {"caller_nid": "cobol_cobol_preprocessor_extractcobolsymbolswithregex", "callee": "push", "is_member_call": true, "source_file": "D:\\temp\\devorbit\\GitNexus\\gitnexus\\src\\core\\ingestion\\cobol\\cobol-preprocessor.ts", "source_location": "L1208"}, {"caller_nid": "cobol_cobol_preprocessor_extractcobolsymbolswithregex", "callee": "pop", "is_member_call": true, "source_file": "D:\\temp\\devorbit\\GitNexus\\gitnexus\\src\\core\\ingestion\\cobol\\cobol-preprocessor.ts", "source_location": "L1215"}, {"caller_nid": "cobol_cobol_preprocessor_extractcobolsymbolswithregex", "callee": "push", "is_member_call": true, "source_file": "D:\\temp\\devorbit\\GitNexus\\gitnexus\\src\\core\\ingestion\\cobol\\cobol-preprocessor.ts", "source_location": "L1216"}, {"caller_nid": "cobol_cobol_preprocessor_extractcobolsymbolswithregex", "callee": "sort", "is_member_call": true, "source_file": "D:\\temp\\devorbit\\GitNexus\\gitnexus\\src\\core\\ingestion\\cobol\\cobol-preprocessor.ts", "source_location": "L1227"}]}