{"nodes": [{"id": "d_temp_devorbit_gitnexus_type_resolution_system_md", "label": "type-resolution-system.md", "file_type": "document", "source_file": "D:\\temp\\devorbit\\GitNexus\\type-resolution-system.md", "source_location": "L1"}, {"id": "gitnexus_type_resolution_system_type_resolution_system", "label": "Type Resolution System", "file_type": "document", "source_file": "D:\\temp\\devorbit\\GitNexus\\type-resolution-system.md", "source_location": "L1"}, {"id": "gitnexus_type_resolution_system_purpose_in_the_pipeline", "label": "Purpose in the Pipeline", "file_type": "document", "source_file": "D:\\temp\\devorbit\\GitNexus\\type-resolution-system.md", "source_location": "L18"}, {"id": "gitnexus_type_resolution_system_codeblock_1", "label": "code:text (parse-worker.ts)", "file_type": "document", "source_file": "D:\\temp\\devorbit\\GitNexus\\type-resolution-system.md", "source_location": "L22"}, {"id": "gitnexus_type_resolution_system_architecture", "label": "Architecture", "file_type": "document", "source_file": "D:\\temp\\devorbit\\GitNexus\\type-resolution-system.md", "source_location": "L45"}, {"id": "gitnexus_type_resolution_system_codeblock_2", "label": "code:text (\u250c\u2500\u2500\u2500\u2500\u2500\u2500\u2500\u2500\u2500\u2500\u2500\u2500\u2500\u2500\u2500\u2500\u2500\u2500\u2500\u2500\u2500\u2500\u2510)", "file_type": "document", "source_file": "D:\\temp\\devorbit\\GitNexus\\type-resolution-system.md", "source_location": "L47"}, {"id": "gitnexus_type_resolution_system_main_files", "label": "Main files", "file_type": "document", "source_file": "D:\\temp\\devorbit\\GitNexus\\type-resolution-system.md", "source_location": "L68"}, {"id": "gitnexus_type_resolution_system_supported_languages", "label": "Supported Languages", "file_type": "document", "source_file": "D:\\temp\\devorbit\\GitNexus\\type-resolution-system.md", "source_location": "L89"}, {"id": "gitnexus_type_resolution_system_design_constraints", "label": "Design Constraints", "file_type": "document", "source_file": "D:\\temp\\devorbit\\GitNexus\\type-resolution-system.md", "source_location": "L111"}, {"id": "gitnexus_type_resolution_system_typeenvironment_model", "label": "TypeEnvironment Model", "file_type": "document", "source_file": "D:\\temp\\devorbit\\GitNexus\\type-resolution-system.md", "source_location": "L137"}, {"id": "gitnexus_type_resolution_system_scope_model", "label": "Scope model", "file_type": "document", "source_file": "D:\\temp\\devorbit\\GitNexus\\type-resolution-system.md", "source_location": "L146"}, {"id": "gitnexus_type_resolution_system_codeblock_3", "label": "code:text (File scope (''))", "file_type": "document", "source_file": "D:\\temp\\devorbit\\GitNexus\\type-resolution-system.md", "source_location": "L150"}, {"id": "gitnexus_type_resolution_system_scope_keys", "label": "Scope keys", "file_type": "document", "source_file": "D:\\temp\\devorbit\\GitNexus\\type-resolution-system.md", "source_location": "L163"}, {"id": "gitnexus_type_resolution_system_lookup_semantics", "label": "Lookup Semantics", "file_type": "document", "source_file": "D:\\temp\\devorbit\\GitNexus\\type-resolution-system.md", "source_location": "L172"}, {"id": "gitnexus_type_resolution_system_resolution_tiers", "label": "Resolution Tiers", "file_type": "document", "source_file": "D:\\temp\\devorbit\\GitNexus\\type-resolution-system.md", "source_location": "L187"}, {"id": "gitnexus_type_resolution_system_tier_0_explicit_type_annotations", "label": "Tier 0: Explicit Type Annotations", "file_type": "document", "source_file": "D:\\temp\\devorbit\\GitNexus\\type-resolution-system.md", "source_location": "L191"}, {"id": "gitnexus_type_resolution_system_codeblock_4", "label": "code:typescript (// TypeScript)", "file_type": "document", "source_file": "D:\\temp\\devorbit\\GitNexus\\type-resolution-system.md", "source_location": "L195"}, {"id": "gitnexus_type_resolution_system_tier_0b_for_loop_element_type_resolution", "label": "Tier 0b: For-Loop Element Type Resolution", "file_type": "document", "source_file": "D:\\temp\\devorbit\\GitNexus\\type-resolution-system.md", "source_location": "L216"}, {"id": "gitnexus_type_resolution_system_codeblock_5", "label": "code:csharp (foreach (var user in users) { user.Save(); })", "file_type": "document", "source_file": "D:\\temp\\devorbit\\GitNexus\\type-resolution-system.md", "source_location": "L222"}, {"id": "gitnexus_type_resolution_system_tier_0c_pattern_binding", "label": "Tier 0c: Pattern Binding", "file_type": "document", "source_file": "D:\\temp\\devorbit\\GitNexus\\type-resolution-system.md", "source_location": "L243"}, {"id": "gitnexus_type_resolution_system_codeblock_6", "label": "code:csharp (if (obj is User user) { user.Save(); })", "file_type": "document", "source_file": "D:\\temp\\devorbit\\GitNexus\\type-resolution-system.md", "source_location": "L247"}, {"id": "gitnexus_type_resolution_system_tier_1_initializer_constructor_inference", "label": "Tier 1: Initializer / Constructor Inference", "file_type": "document", "source_file": "D:\\temp\\devorbit\\GitNexus\\type-resolution-system.md", "source_location": "L267"}, {"id": "gitnexus_type_resolution_system_codeblock_7", "label": "code:typescript (const user = new User())", "file_type": "document", "source_file": "D:\\temp\\devorbit\\GitNexus\\type-resolution-system.md", "source_location": "L271"}, {"id": "gitnexus_type_resolution_system_tier_2_assignment_chain_propagation", "label": "Tier 2: Assignment Chain Propagation", "file_type": "document", "source_file": "D:\\temp\\devorbit\\GitNexus\\type-resolution-system.md", "source_location": "L293"}, {"id": "gitnexus_type_resolution_system_codeblock_8", "label": "code:typescript (const user: User = getUser())", "file_type": "document", "source_file": "D:\\temp\\devorbit\\GitNexus\\type-resolution-system.md", "source_location": "L297"}, {"id": "gitnexus_type_resolution_system_codeblock_9", "label": "code:typescript (const b = a              // iteration 2: b \u2192 User (a now res)", "file_type": "document", "source_file": "D:\\temp\\devorbit\\GitNexus\\type-resolution-system.md", "source_location": "L305"}, {"id": "gitnexus_type_resolution_system_codeblock_10", "label": "code:typescript (const user = getUser()       // callResult \u2192 User)", "file_type": "document", "source_file": "D:\\temp\\devorbit\\GitNexus\\type-resolution-system.md", "source_location": "L312"}, {"id": "gitnexus_type_resolution_system_container_type_descriptors", "label": "Container Type Descriptors", "file_type": "document", "source_file": "D:\\temp\\devorbit\\GitNexus\\type-resolution-system.md", "source_location": "L320"}, {"id": "gitnexus_type_resolution_system_codeblock_11", "label": "code:typescript (for (const key of map.keys()) { ... }    // key \u2192 string)", "file_type": "document", "source_file": "D:\\temp\\devorbit\\GitNexus\\type-resolution-system.md", "source_location": "L326"}, {"id": "gitnexus_type_resolution_system_examples_of_descriptor_driven_behavior", "label": "Examples of descriptor-driven behavior", "file_type": "document", "source_file": "D:\\temp\\devorbit\\GitNexus\\type-resolution-system.md", "source_location": "L333"}, {"id": "gitnexus_type_resolution_system_comment_based_types", "label": "Comment-Based Types", "file_type": "document", "source_file": "D:\\temp\\devorbit\\GitNexus\\type-resolution-system.md", "source_location": "L341"}, {"id": "gitnexus_type_resolution_system_symboltable_interaction", "label": "SymbolTable Interaction", "file_type": "document", "source_file": "D:\\temp\\devorbit\\GitNexus\\type-resolution-system.md", "source_location": "L355"}, {"id": "gitnexus_type_resolution_system_deferred_binding_verification_in_call_processing", "label": "Deferred Binding Verification in Call Processing", "file_type": "document", "source_file": "D:\\temp\\devorbit\\GitNexus\\type-resolution-system.md", "source_location": "L365"}, {"id": "gitnexus_type_resolution_system_language_feature_matrix", "label": "Language Feature Matrix", "file_type": "document", "source_file": "D:\\temp\\devorbit\\GitNexus\\type-resolution-system.md", "source_location": "L378"}, {"id": "gitnexus_type_resolution_system_current_strengths", "label": "Current Strengths", "file_type": "document", "source_file": "D:\\temp\\devorbit\\GitNexus\\type-resolution-system.md", "source_location": "L436"}, {"id": "gitnexus_type_resolution_system_current_limitations", "label": "Current Limitations", "file_type": "document", "source_file": "D:\\temp\\devorbit\\GitNexus\\type-resolution-system.md", "source_location": "L460"}, {"id": "gitnexus_type_resolution_system_contributor_notes", "label": "Contributor Notes", "file_type": "document", "source_file": "D:\\temp\\devorbit\\GitNexus\\type-resolution-system.md", "source_location": "L475"}], "edges": [{"source": "d_temp_devorbit_gitnexus_type_resolution_system_md", "target": "gitnexus_type_resolution_system_type_resolution_system", "relation": "contains", "confidence": "EXTRACTED", "source_file": "D:\\temp\\devorbit\\GitNexus\\type-resolution-system.md", "source_location": "L1", "weight": 1.0}, {"source": "gitnexus_type_resolution_system_type_resolution_system", "target": "gitnexus_type_resolution_system_purpose_in_the_pipeline", "relation": "contains", "confidence": "EXTRACTED", "source_file": "D:\\temp\\devorbit\\GitNexus\\type-resolution-system.md", "source_location": "L18", "weight": 1.0}, {"source": "gitnexus_type_resolution_system_purpose_in_the_pipeline", "target": "gitnexus_type_resolution_system_codeblock_1", "relation": "contains", "confidence": "EXTRACTED", "source_file": "D:\\temp\\devorbit\\GitNexus\\type-resolution-system.md", "source_location": "L22", "weight": 1.0}, {"source": "gitnexus_type_resolution_system_type_resolution_system", "target": "gitnexus_type_resolution_system_architecture", "relation": "contains", "confidence": "EXTRACTED", "source_file": "D:\\temp\\devorbit\\GitNexus\\type-resolution-system.md", "source_location": "L45", "weight": 1.0}, {"source": "gitnexus_type_resolution_system_architecture", "target": "gitnexus_type_resolution_system_codeblock_2", "relation": "contains", "confidence": "EXTRACTED", "source_file": "D:\\temp\\devorbit\\GitNexus\\type-resolution-system.md", "source_location": "L47", "weight": 1.0}, {"source": "gitnexus_type_resolution_system_architecture", "target": "gitnexus_type_resolution_system_main_files", "relation": "contains", "confidence": "EXTRACTED", "source_file": "D:\\temp\\devorbit\\GitNexus\\type-resolution-system.md", "source_location": "L68", "weight": 1.0}, {"source": "gitnexus_type_resolution_system_type_resolution_system", "target": "gitnexus_type_resolution_system_supported_languages", "relation": "contains", "confidence": "EXTRACTED", "source_file": "D:\\temp\\devorbit\\GitNexus\\type-resolution-system.md", "source_location": "L89", "weight": 1.0}, {"source": "gitnexus_type_resolution_system_type_resolution_system", "target": "gitnexus_type_resolution_system_design_constraints", "relation": "contains", "confidence": "EXTRACTED", "source_file": "D:\\temp\\devorbit\\GitNexus\\type-resolution-system.md", "source_location": "L111", "weight": 1.0}, {"source": "gitnexus_type_resolution_system_type_resolution_system", "target": "gitnexus_type_resolution_system_typeenvironment_model", "relation": "contains", "confidence": "EXTRACTED", "source_file": "D:\\temp\\devorbit\\GitNexus\\type-resolution-system.md", "source_location": "L137", "weight": 1.0}, {"source": "gitnexus_type_resolution_system_typeenvironment_model", "target": "gitnexus_type_resolution_system_scope_model", "relation": "contains", "confidence": "EXTRACTED", "source_file": "D:\\temp\\devorbit\\GitNexus\\type-resolution-system.md", "source_location": "L146", "weight": 1.0}, {"source": "gitnexus_type_resolution_system_scope_model", "target": "gitnexus_type_resolution_system_codeblock_3", "relation": "contains", "confidence": "EXTRACTED", "source_file": "D:\\temp\\devorbit\\GitNexus\\type-resolution-system.md", "source_location": "L150", "weight": 1.0}, {"source": "gitnexus_type_resolution_system_typeenvironment_model", "target": "gitnexus_type_resolution_system_scope_keys", "relation": "contains", "confidence": "EXTRACTED", "source_file": "D:\\temp\\devorbit\\GitNexus\\type-resolution-system.md", "source_location": "L163", "weight": 1.0}, {"source": "gitnexus_type_resolution_system_type_resolution_system", "target": "gitnexus_type_resolution_system_lookup_semantics", "relation": "contains", "confidence": "EXTRACTED", "source_file": "D:\\temp\\devorbit\\GitNexus\\type-resolution-system.md", "source_location": "L172", "weight": 1.0}, {"source": "gitnexus_type_resolution_system_type_resolution_system", "target": "gitnexus_type_resolution_system_resolution_tiers", "relation": "contains", "confidence": "EXTRACTED", "source_file": "D:\\temp\\devorbit\\GitNexus\\type-resolution-system.md", "source_location": "L187", "weight": 1.0}, {"source": "gitnexus_type_resolution_system_resolution_tiers", "target": "gitnexus_type_resolution_system_tier_0_explicit_type_annotations", "relation": "contains", "confidence": "EXTRACTED", "source_file": "D:\\temp\\devorbit\\GitNexus\\type-resolution-system.md", "source_location": "L191", "weight": 1.0}, {"source": "gitnexus_type_resolution_system_tier_0_explicit_type_annotations", "target": "gitnexus_type_resolution_system_codeblock_4", "relation": "contains", "confidence": "EXTRACTED", "source_file": "D:\\temp\\devorbit\\GitNexus\\type-resolution-system.md", "source_location": "L195", "weight": 1.0}, {"source": "gitnexus_type_resolution_system_resolution_tiers", "target": "gitnexus_type_resolution_system_tier_0b_for_loop_element_type_resolution", "relation": "contains", "confidence": "EXTRACTED", "source_file": "D:\\temp\\devorbit\\GitNexus\\type-resolution-system.md", "source_location": "L216", "weight": 1.0}, {"source": "gitnexus_type_resolution_system_tier_0b_for_loop_element_type_resolution", "target": "gitnexus_type_resolution_system_codeblock_5", "relation": "contains", "confidence": "EXTRACTED", "source_file": "D:\\temp\\devorbit\\GitNexus\\type-resolution-system.md", "source_location": "L222", "weight": 1.0}, {"source": "gitnexus_type_resolution_system_resolution_tiers", "target": "gitnexus_type_resolution_system_tier_0c_pattern_binding", "relation": "contains", "confidence": "EXTRACTED", "source_file": "D:\\temp\\devorbit\\GitNexus\\type-resolution-system.md", "source_location": "L243", "weight": 1.0}, {"source": "gitnexus_type_resolution_system_tier_0c_pattern_binding", "target": "gitnexus_type_resolution_system_codeblock_6", "relation": "contains", "confidence": "EXTRACTED", "source_file": "D:\\temp\\devorbit\\GitNexus\\type-resolution-system.md", "source_location": "L247", "weight": 1.0}, {"source": "gitnexus_type_resolution_system_resolution_tiers", "target": "gitnexus_type_resolution_system_tier_1_initializer_constructor_inference", "relation": "contains", "confidence": "EXTRACTED", "source_file": "D:\\temp\\devorbit\\GitNexus\\type-resolution-system.md", "source_location": "L267", "weight": 1.0}, {"source": "gitnexus_type_resolution_system_tier_1_initializer_constructor_inference", "target": "gitnexus_type_resolution_system_codeblock_7", "relation": "contains", "confidence": "EXTRACTED", "source_file": "D:\\temp\\devorbit\\GitNexus\\type-resolution-system.md", "source_location": "L271", "weight": 1.0}, {"source": "gitnexus_type_resolution_system_resolution_tiers", "target": "gitnexus_type_resolution_system_tier_2_assignment_chain_propagation", "relation": "contains", "confidence": "EXTRACTED", "source_file": "D:\\temp\\devorbit\\GitNexus\\type-resolution-system.md", "source_location": "L293", "weight": 1.0}, {"source": "gitnexus_type_resolution_system_tier_2_assignment_chain_propagation", "target": "gitnexus_type_resolution_system_codeblock_8", "relation": "contains", "confidence": "EXTRACTED", "source_file": "D:\\temp\\devorbit\\GitNexus\\type-resolution-system.md", "source_location": "L297", "weight": 1.0}, {"source": "gitnexus_type_resolution_system_tier_2_assignment_chain_propagation", "target": "gitnexus_type_resolution_system_codeblock_9", "relation": "contains", "confidence": "EXTRACTED", "source_file": "D:\\temp\\devorbit\\GitNexus\\type-resolution-system.md", "source_location": "L305", "weight": 1.0}, {"source": "gitnexus_type_resolution_system_tier_2_assignment_chain_propagation", "target": "gitnexus_type_resolution_system_codeblock_10", "relation": "contains", "confidence": "EXTRACTED", "source_file": "D:\\temp\\devorbit\\GitNexus\\type-resolution-system.md", "source_location": "L312", "weight": 1.0}, {"source": "gitnexus_type_resolution_system_type_resolution_system", "target": "gitnexus_type_resolution_system_container_type_descriptors", "relation": "contains", "confidence": "EXTRACTED", "source_file": "D:\\temp\\devorbit\\GitNexus\\type-resolution-system.md", "source_location": "L320", "weight": 1.0}, {"source": "gitnexus_type_resolution_system_container_type_descriptors", "target": "gitnexus_type_resolution_system_codeblock_11", "relation": "contains", "confidence": "EXTRACTED", "source_file": "D:\\temp\\devorbit\\GitNexus\\type-resolution-system.md", "source_location": "L326", "weight": 1.0}, {"source": "gitnexus_type_resolution_system_container_type_descriptors", "target": "gitnexus_type_resolution_system_examples_of_descriptor_driven_behavior", "relation": "contains", "confidence": "EXTRACTED", "source_file": "D:\\temp\\devorbit\\GitNexus\\type-resolution-system.md", "source_location": "L333", "weight": 1.0}, {"source": "gitnexus_type_resolution_system_type_resolution_system", "target": "gitnexus_type_resolution_system_comment_based_types", "relation": "contains", "confidence": "EXTRACTED", "source_file": "D:\\temp\\devorbit\\GitNexus\\type-resolution-system.md", "source_location": "L341", "weight": 1.0}, {"source": "gitnexus_type_resolution_system_type_resolution_system", "target": "gitnexus_type_resolution_system_symboltable_interaction", "relation": "contains", "confidence": "EXTRACTED", "source_file": "D:\\temp\\devorbit\\GitNexus\\type-resolution-system.md", "source_location": "L355", "weight": 1.0}, {"source": "gitnexus_type_resolution_system_type_resolution_system", "target": "gitnexus_type_resolution_system_deferred_binding_verification_in_call_processing", "relation": "contains", "confidence": "EXTRACTED", "source_file": "D:\\temp\\devorbit\\GitNexus\\type-resolution-system.md", "source_location": "L365", "weight": 1.0}, {"source": "gitnexus_type_resolution_system_type_resolution_system", "target": "gitnexus_type_resolution_system_language_feature_matrix", "relation": "contains", "confidence": "EXTRACTED", "source_file": "D:\\temp\\devorbit\\GitNexus\\type-resolution-system.md", "source_location": "L378", "weight": 1.0}, {"source": "gitnexus_type_resolution_system_type_resolution_system", "target": "gitnexus_type_resolution_system_current_strengths", "relation": "contains", "confidence": "EXTRACTED", "source_file": "D:\\temp\\devorbit\\GitNexus\\type-resolution-system.md", "source_location": "L436", "weight": 1.0}, {"source": "gitnexus_type_resolution_system_type_resolution_system", "target": "gitnexus_type_resolution_system_current_limitations", "relation": "contains", "confidence": "EXTRACTED", "source_file": "D:\\temp\\devorbit\\GitNexus\\type-resolution-system.md", "source_location": "L460", "weight": 1.0}, {"source": "gitnexus_type_resolution_system_type_resolution_system", "target": "gitnexus_type_resolution_system_contributor_notes", "relation": "contains", "confidence": "EXTRACTED", "source_file": "D:\\temp\\devorbit\\GitNexus\\type-resolution-system.md", "source_location": "L475", "weight": 1.0}], "input_tokens": 0, "output_tokens": 0}