{"nodes": [{"id": "d_temp_devorbit_gitnexus_gitnexus_test_unit_resolve_enclosing_owner_test_ts", "label": "resolve-enclosing-owner.test.ts", "file_type": "code", "source_file": "D:\\temp\\devorbit\\GitNexus\\gitnexus\\test\\unit\\resolve-enclosing-owner.test.ts", "source_location": "L1"}, {"id": "unit_resolve_enclosing_owner_test_parser", "label": "parser", "file_type": "code", "source_file": "D:\\temp\\devorbit\\GitNexus\\gitnexus\\test\\unit\\resolve-enclosing-owner.test.ts", "source_location": "L23"}, {"id": "unit_resolve_enclosing_owner_test_parseruby", "label": "parseRuby()", "file_type": "code", "source_file": "D:\\temp\\devorbit\\GitNexus\\gitnexus\\test\\unit\\resolve-enclosing-owner.test.ts", "source_location": "L25"}, {"id": "unit_resolve_enclosing_owner_test_parsekotlin", "label": "parseKotlin()", "file_type": "code", "source_file": "D:\\temp\\devorbit\\GitNexus\\gitnexus\\test\\unit\\resolve-enclosing-owner.test.ts", "source_location": "L30"}, {"id": "unit_resolve_enclosing_owner_test_tree", "label": "tree", "file_type": "code", "source_file": "D:\\temp\\devorbit\\GitNexus\\gitnexus\\test\\unit\\resolve-enclosing-owner.test.ts", "source_location": "L41"}, {"id": "unit_resolve_enclosing_owner_test_info", "label": "info", "file_type": "code", "source_file": "D:\\temp\\devorbit\\GitNexus\\gitnexus\\test\\unit\\resolve-enclosing-owner.test.ts", "source_location": "L56"}, {"id": "unit_resolve_enclosing_owner_test_start", "label": "start", "file_type": "code", "source_file": "D:\\temp\\devorbit\\GitNexus\\gitnexus\\test\\unit\\resolve-enclosing-owner.test.ts", "source_location": "L210"}], "edges": [{"source": "d_temp_devorbit_gitnexus_gitnexus_test_unit_resolve_enclosing_owner_test_ts", "target": "vitest", "relation": "imports_from", "context": "import", "confidence": "EXTRACTED", "source_file": "D:\\temp\\devorbit\\GitNexus\\gitnexus\\test\\unit\\resolve-enclosing-owner.test.ts", "source_location": "L10", "weight": 1.0}, {"source": "d_temp_devorbit_gitnexus_gitnexus_test_unit_resolve_enclosing_owner_test_ts", "target": "tree_sitter", "relation": "imports_from", "context": "import", "confidence": "EXTRACTED", "source_file": "D:\\temp\\devorbit\\GitNexus\\gitnexus\\test\\unit\\resolve-enclosing-owner.test.ts", "source_location": "L11", "weight": 1.0}, {"source": "d_temp_devorbit_gitnexus_gitnexus_test_unit_resolve_enclosing_owner_test_ts", "target": "tree_sitter_ruby", "relation": "imports_from", "context": "import", "confidence": "EXTRACTED", "source_file": "D:\\temp\\devorbit\\GitNexus\\gitnexus\\test\\unit\\resolve-enclosing-owner.test.ts", "source_location": "L12", "weight": 1.0}, {"source": "d_temp_devorbit_gitnexus_gitnexus_test_unit_resolve_enclosing_owner_test_ts", "target": "d_temp_devorbit_gitnexus_gitnexus_src_core_ingestion_utils_ast_helpers_ts", "relation": "imports_from", "context": "import", "confidence": "EXTRACTED", "source_file": "D:\\temp\\devorbit\\GitNexus\\gitnexus\\test\\unit\\resolve-enclosing-owner.test.ts", "source_location": "L13", "weight": 1.0}, {"source": "d_temp_devorbit_gitnexus_gitnexus_test_unit_resolve_enclosing_owner_test_ts", "target": "utils_ast_helpers_findenclosingclassinfo", "relation": "imports", "context": "import", "confidence": "EXTRACTED", "source_file": "D:\\temp\\devorbit\\GitNexus\\gitnexus\\test\\unit\\resolve-enclosing-owner.test.ts", "source_location": "L13", "weight": 1.0}, {"source": "d_temp_devorbit_gitnexus_gitnexus_test_unit_resolve_enclosing_owner_test_ts", "target": "d_temp_devorbit_gitnexus_gitnexus_src_core_ingestion_languages_ruby_ts", "relation": "imports_from", "context": "import", "confidence": "EXTRACTED", "source_file": "D:\\temp\\devorbit\\GitNexus\\gitnexus\\test\\unit\\resolve-enclosing-owner.test.ts", "source_location": "L14", "weight": 1.0}, {"source": "d_temp_devorbit_gitnexus_gitnexus_test_unit_resolve_enclosing_owner_test_ts", "target": "languages_ruby_rubyprovider", "relation": "imports", "context": "import", "confidence": "EXTRACTED", "source_file": "D:\\temp\\devorbit\\GitNexus\\gitnexus\\test\\unit\\resolve-enclosing-owner.test.ts", "source_location": "L14", "weight": 1.0}, {"source": "d_temp_devorbit_gitnexus_gitnexus_test_unit_resolve_enclosing_owner_test_ts", "target": "unit_resolve_enclosing_owner_test_parser", "relation": "contains", "confidence": "EXTRACTED", "source_file": "D:\\temp\\devorbit\\GitNexus\\gitnexus\\test\\unit\\resolve-enclosing-owner.test.ts", "source_location": "L23", "weight": 1.0}, {"source": "d_temp_devorbit_gitnexus_gitnexus_test_unit_resolve_enclosing_owner_test_ts", "target": "unit_resolve_enclosing_owner_test_parseruby", "relation": "contains", "confidence": "EXTRACTED", "source_file": "D:\\temp\\devorbit\\GitNexus\\gitnexus\\test\\unit\\resolve-enclosing-owner.test.ts", "source_location": "L25", "weight": 1.0}, {"source": "d_temp_devorbit_gitnexus_gitnexus_test_unit_resolve_enclosing_owner_test_ts", "target": "unit_resolve_enclosing_owner_test_parsekotlin", "relation": "contains", "confidence": "EXTRACTED", "source_file": "D:\\temp\\devorbit\\GitNexus\\gitnexus\\test\\unit\\resolve-enclosing-owner.test.ts", "source_location": "L30", "weight": 1.0}, {"source": "d_temp_devorbit_gitnexus_gitnexus_test_unit_resolve_enclosing_owner_test_ts", "target": "unit_resolve_enclosing_owner_test_tree", "relation": "contains", "confidence": "EXTRACTED", "source_file": "D:\\temp\\devorbit\\GitNexus\\gitnexus\\test\\unit\\resolve-enclosing-owner.test.ts", "source_location": "L41", "weight": 1.0}, {"source": "d_temp_devorbit_gitnexus_gitnexus_test_unit_resolve_enclosing_owner_test_ts", "target": "unit_resolve_enclosing_owner_test_info", "relation": "contains", "confidence": "EXTRACTED", "source_file": "D:\\temp\\devorbit\\GitNexus\\gitnexus\\test\\unit\\resolve-enclosing-owner.test.ts", "source_location": "L56", "weight": 1.0}, {"source": "d_temp_devorbit_gitnexus_gitnexus_test_unit_resolve_enclosing_owner_test_ts", "target": "unit_resolve_enclosing_owner_test_tree", "relation": "contains", "confidence": "EXTRACTED", "source_file": "D:\\temp\\devorbit\\GitNexus\\gitnexus\\test\\unit\\resolve-enclosing-owner.test.ts", "source_location": "L68", "weight": 1.0}, {"source": "d_temp_devorbit_gitnexus_gitnexus_test_unit_resolve_enclosing_owner_test_ts", "target": "unit_resolve_enclosing_owner_test_info", "relation": "contains", "confidence": "EXTRACTED", "source_file": "D:\\temp\\devorbit\\GitNexus\\gitnexus\\test\\unit\\resolve-enclosing-owner.test.ts", "source_location": "L82", "weight": 1.0}, {"source": "d_temp_devorbit_gitnexus_gitnexus_test_unit_resolve_enclosing_owner_test_ts", "target": "unit_resolve_enclosing_owner_test_tree", "relation": "contains", "confidence": "EXTRACTED", "source_file": "D:\\temp\\devorbit\\GitNexus\\gitnexus\\test\\unit\\resolve-enclosing-owner.test.ts", "source_location": "L97", "weight": 1.0}, {"source": "d_temp_devorbit_gitnexus_gitnexus_test_unit_resolve_enclosing_owner_test_ts", "target": "unit_resolve_enclosing_owner_test_info", "relation": "contains", "confidence": "EXTRACTED", "source_file": "D:\\temp\\devorbit\\GitNexus\\gitnexus\\test\\unit\\resolve-enclosing-owner.test.ts", "source_location": "L107", "weight": 1.0}, {"source": "d_temp_devorbit_gitnexus_gitnexus_test_unit_resolve_enclosing_owner_test_ts", "target": "unit_resolve_enclosing_owner_test_tree", "relation": "contains", "confidence": "EXTRACTED", "source_file": "D:\\temp\\devorbit\\GitNexus\\gitnexus\\test\\unit\\resolve-enclosing-owner.test.ts", "source_location": "L118", "weight": 1.0}, {"source": "d_temp_devorbit_gitnexus_gitnexus_test_unit_resolve_enclosing_owner_test_ts", "target": "unit_resolve_enclosing_owner_test_info", "relation": "contains", "confidence": "EXTRACTED", "source_file": "D:\\temp\\devorbit\\GitNexus\\gitnexus\\test\\unit\\resolve-enclosing-owner.test.ts", "source_location": "L128", "weight": 1.0}, {"source": "d_temp_devorbit_gitnexus_gitnexus_test_unit_resolve_enclosing_owner_test_ts", "target": "unit_resolve_enclosing_owner_test_tree", "relation": "contains", "confidence": "EXTRACTED", "source_file": "D:\\temp\\devorbit\\GitNexus\\gitnexus\\test\\unit\\resolve-enclosing-owner.test.ts", "source_location": "L141", "weight": 1.0}, {"source": "d_temp_devorbit_gitnexus_gitnexus_test_unit_resolve_enclosing_owner_test_ts", "target": "unit_resolve_enclosing_owner_test_info", "relation": "contains", "confidence": "EXTRACTED", "source_file": "D:\\temp\\devorbit\\GitNexus\\gitnexus\\test\\unit\\resolve-enclosing-owner.test.ts", "source_location": "L155", "weight": 1.0}, {"source": "d_temp_devorbit_gitnexus_gitnexus_test_unit_resolve_enclosing_owner_test_ts", "target": "unit_resolve_enclosing_owner_test_tree", "relation": "contains", "confidence": "EXTRACTED", "source_file": "D:\\temp\\devorbit\\GitNexus\\gitnexus\\test\\unit\\resolve-enclosing-owner.test.ts", "source_location": "L163", "weight": 1.0}, {"source": "d_temp_devorbit_gitnexus_gitnexus_test_unit_resolve_enclosing_owner_test_ts", "target": "unit_resolve_enclosing_owner_test_info", "relation": "contains", "confidence": "EXTRACTED", "source_file": "D:\\temp\\devorbit\\GitNexus\\gitnexus\\test\\unit\\resolve-enclosing-owner.test.ts", "source_location": "L172", "weight": 1.0}, {"source": "d_temp_devorbit_gitnexus_gitnexus_test_unit_resolve_enclosing_owner_test_ts", "target": "unit_resolve_enclosing_owner_test_tree", "relation": "contains", "confidence": "EXTRACTED", "source_file": "D:\\temp\\devorbit\\GitNexus\\gitnexus\\test\\unit\\resolve-enclosing-owner.test.ts", "source_location": "L194", "weight": 1.0}, {"source": "d_temp_devorbit_gitnexus_gitnexus_test_unit_resolve_enclosing_owner_test_ts", "target": "unit_resolve_enclosing_owner_test_start", "relation": "contains", "confidence": "EXTRACTED", "source_file": "D:\\temp\\devorbit\\GitNexus\\gitnexus\\test\\unit\\resolve-enclosing-owner.test.ts", "source_location": "L210", "weight": 1.0}, {"source": "d_temp_devorbit_gitnexus_gitnexus_test_unit_resolve_enclosing_owner_test_ts", "target": "unit_resolve_enclosing_owner_test_info", "relation": "contains", "confidence": "EXTRACTED", "source_file": "D:\\temp\\devorbit\\GitNexus\\gitnexus\\test\\unit\\resolve-enclosing-owner.test.ts", "source_location": "L215", "weight": 1.0}, {"source": "d_temp_devorbit_gitnexus_gitnexus_test_unit_resolve_enclosing_owner_test_ts", "target": "unit_resolve_enclosing_owner_test_tree", "relation": "contains", "confidence": "EXTRACTED", "source_file": "D:\\temp\\devorbit\\GitNexus\\gitnexus\\test\\unit\\resolve-enclosing-owner.test.ts", "source_location": "L239", "weight": 1.0}, {"source": "d_temp_devorbit_gitnexus_gitnexus_test_unit_resolve_enclosing_owner_test_ts", "target": "unit_resolve_enclosing_owner_test_start", "relation": "contains", "confidence": "EXTRACTED", "source_file": "D:\\temp\\devorbit\\GitNexus\\gitnexus\\test\\unit\\resolve-enclosing-owner.test.ts", "source_location": "L250", "weight": 1.0}, {"source": "d_temp_devorbit_gitnexus_gitnexus_test_unit_resolve_enclosing_owner_test_ts", "target": "unit_resolve_enclosing_owner_test_info", "relation": "contains", "confidence": "EXTRACTED", "source_file": "D:\\temp\\devorbit\\GitNexus\\gitnexus\\test\\unit\\resolve-enclosing-owner.test.ts", "source_location": "L251", "weight": 1.0}, {"source": "d_temp_devorbit_gitnexus_gitnexus_test_unit_resolve_enclosing_owner_test_ts", "target": "unit_resolve_enclosing_owner_test_tree", "relation": "contains", "confidence": "EXTRACTED", "source_file": "D:\\temp\\devorbit\\GitNexus\\gitnexus\\test\\unit\\resolve-enclosing-owner.test.ts", "source_location": "L273", "weight": 1.0}, {"source": "d_temp_devorbit_gitnexus_gitnexus_test_unit_resolve_enclosing_owner_test_ts", "target": "unit_resolve_enclosing_owner_test_info", "relation": "contains", "confidence": "EXTRACTED", "source_file": "D:\\temp\\devorbit\\GitNexus\\gitnexus\\test\\unit\\resolve-enclosing-owner.test.ts", "source_location": "L284", "weight": 1.0}], "raw_calls": [{"caller_nid": "unit_resolve_enclosing_owner_test_parseruby", "callee": "setLanguage", "is_member_call": true, "source_file": "D:\\temp\\devorbit\\GitNexus\\gitnexus\\test\\unit\\resolve-enclosing-owner.test.ts", "source_location": "L26"}, {"caller_nid": "unit_resolve_enclosing_owner_test_parseruby", "callee": "parse", "is_member_call": true, "source_file": "D:\\temp\\devorbit\\GitNexus\\gitnexus\\test\\unit\\resolve-enclosing-owner.test.ts", "source_location": "L27"}, {"caller_nid": "unit_resolve_enclosing_owner_test_parsekotlin", "callee": "setLanguage", "is_member_call": true, "source_file": "D:\\temp\\devorbit\\GitNexus\\gitnexus\\test\\unit\\resolve-enclosing-owner.test.ts", "source_location": "L31"}, {"caller_nid": "unit_resolve_enclosing_owner_test_parsekotlin", "callee": "parse", "is_member_call": true, "source_file": "D:\\temp\\devorbit\\GitNexus\\gitnexus\\test\\unit\\resolve-enclosing-owner.test.ts", "source_location": "L32"}]}